annotated_dataset/__init__.py
annotated_dataset/annotated_dataset.py
annotated_dataset/annotated_resource_base.py
annotated_dataset/annotated_resource_uima_cas_xmi.py
annotated_dataset/annotated_text.py
annotated_dataset/annotated_text_validation_error_report.py
annotated_dataset/annotation.py
annotated_dataset/annotation_schema.py
annotated_dataset/export.py
annotated_dataset/export_annotated_texts_to_tsv.py
annotated_dataset/export_annotated_texts_to_xmi.py
annotated_dataset/find_email.py
annotated_dataset/find_url.py
annotated_dataset/inception_client.py
annotated_dataset/inception_project.py
annotated_dataset/nested_annotation.py
annotated_dataset/validator_ada.py
annotated_dataset/validator_base.py
annotated_dataset/validator_mapa.py
annotated_dataset-0.0.8.dist-info/METADATA
annotated_dataset-0.0.8.dist-info/WHEEL
annotated_dataset-0.0.8.dist-info/top_level.txt
annotated_dataset-0.0.8.dist-info/RECORD
