Metadata-Version: 2.1
Name: annotated-dataset
Version: 0.0.8
Summary: Annotated dataset analysis
Home-page: https://github.com/pangeamt/annotated_dataset
Author: Laurent Bié
Author-email: l.bie@pangeanic.com  
License: UNKNOWN
Platform: UNKNOWN
Classifier: Programming Language :: Python :: 3
Classifier: License :: OSI Approved :: MIT License
Classifier: Operating System :: OS Independent
Requires-Python: >=3.7
Requires-Dist: dkpro-cassis (>=0.5.0)
Requires-Dist: dkpro-cassis-tools (>=0.0.6)
Requires-Dist: networkx (>=2.5)
Requires-Dist: pycaprio (>=0.2.0)
Requires-Dist: web-anno-tsv (>=0.0.1)
Requires-Dist: bokeh (>=2.2.3)
